belton/__init__.py
belton/__main__.py
belton/cli.py
belton/commands/__init__.py
belton/commands/calc_cmd.py
belton/commands/config_cmd.py
belton/commands/import_cmd.py
belton/constants.py
belt_on-0.0.0.dist-info/METADATA
belt_on-0.0.0.dist-info/WHEEL
belt_on-0.0.0.dist-info/entry_points.txt
belt_on-0.0.0.dist-info/licenses/LICENSE
belt_on-0.0.0.dist-info/RECORD
