Metadata-Version: 2.4
Name: belt-on
Version: 0.0.0
Summary: Throughput calculations for factory games.
License-File: LICENSE
Keywords: automation,games,factory
Author: Apathetic Tools
Requires-Python: >=3.14
Classifier: Development Status :: 3 - Alpha
Classifier: Environment :: Console
Classifier: Intended Audience :: End Users/Desktop
Classifier: Operating System :: OS Independent
Classifier: Programming Language :: Python :: 3
Classifier: Programming Language :: Python :: 3 :: Only
Classifier: Programming Language :: Python :: 3.14
Classifier: Topic :: Games/Entertainment :: Simulation
Requires-Dist: jsonschema (>=4.25.1,<5.0.0)
Requires-Dist: platformdirs (>=4.5.1,<5.0.0)
Requires-Dist: tomli-w (>=1.0.0,<2.0.0)
Requires-Dist: typer (>=0.20.0,<0.21.0)
Project-URL: Changelog, https://github.com/apathetic-tools/belt-on/releases
Project-URL: Documentation, https://apathetic-tools.github.io/belt-on/
Project-URL: Homepage, https://github.com/apathetic-tools/belt-on
Project-URL: Issues, https://github.com/apathetic-tools/belt-on/issues
Project-URL: Repository, https://github.com/apathetic-tools/belt-on
